mscz/mscz.py
mscz-0.0.1.dist-info/LICENSE
mscz-0.0.1.dist-info/METADATA
mscz-0.0.1.dist-info/WHEEL
mscz-0.0.1.dist-info/top_level.txt
mscz-0.0.1.dist-info/RECORD
